extractorblog/__init__.py
extractorblog/__version__.py
extractorblog/api.py
extractorblog/extractorblog.py
extractorblog/main_extractor.py
extractorblog/readability.py
extractorblog/tomd.py
extractorblog-0.0.3.dist-info/METADATA
extractorblog-0.0.3.dist-info/WHEEL
extractorblog-0.0.3.dist-info/top_level.txt
extractorblog-0.0.3.dist-info/zip-safe
extractorblog-0.0.3.dist-info/RECORD
