Metadata-Version: 2.1
Name: extractorblog
Version: 0.0.3
Summary: extractor blog
Home-page: https://github.com/SunJackson/extractor-blog
Author: JacksonSun
Author-email: jacksonsunjj@gmail.com
License: MIT
Keywords: blog extractor text keywords
Platform: UNKNOWN
Classifier: License :: OSI Approved :: MIT License
Classifier: Programming Language :: Python
Classifier: Intended Audience :: Developers
Classifier: Operating System :: OS Independent
Requires-Dist: requests
Requires-Dist: chardet
Requires-Dist: beautifulsoup4
